fenrir_api/__init__.py
fenrir_api/api_client.py
fenrir_api/api_response.py
fenrir_api/configuration.py
fenrir_api/exceptions.py
fenrir_api/py.typed
fenrir_api/rest.py
fenrir_api/api/__init__.py
fenrir_api/api/fenrir_api.py
fenrir_api/models/__init__.py
fenrir_api/models/api_token.py
fenrir_api/models/api_token_list_response.py
fenrir_api/models/api_token_response.py
fenrir_api/models/application.py
fenrir_api/models/application_configuration.py
fenrir_api/models/application_configuration_list_response.py
fenrir_api/models/application_configuration_response.py
fenrir_api/models/application_instance.py
fenrir_api/models/application_instance_list_response.py
fenrir_api/models/application_instance_port.py
fenrir_api/models/application_instance_response.py
fenrir_api/models/application_instance_stats.py
fenrir_api/models/application_list_response.py
fenrir_api/models/application_response.py
fenrir_api/models/application_stats.py
fenrir_api/models/application_stats_response.py
fenrir_api/models/bad_request_response.py
fenrir_api/models/deployment.py
fenrir_api/models/deployment_list_response.py
fenrir_api/models/deployment_response.py
fenrir_api/models/deployment_stats.py
fenrir_api/models/deployment_stats_response.py
fenrir_api/models/image.py
fenrir_api/models/image_list_response.py
fenrir_api/models/instance_logs.py
fenrir_api/models/instance_logs_preview.py
fenrir_api/models/matchmaking_queue.py
fenrir_api/models/matchmaking_queue_configuration.py
fenrir_api/models/matchmaking_queue_configuration_list_response.py
fenrir_api/models/matchmaking_queue_configuration_player_property.py
fenrir_api/models/matchmaking_queue_configuration_player_rule.py
fenrir_api/models/matchmaking_queue_configuration_response.py
fenrir_api/models/matchmaking_queue_configuration_team.py
fenrir_api/models/matchmaking_queue_configuration_team_rule.py
fenrir_api/models/matchmaking_queue_list_response.py
fenrir_api/models/matchmaking_queue_response.py
fenrir_api/models/not_found_response.py
fenrir_api-0.1.4.dist-info/METADATA
fenrir_api-0.1.4.dist-info/WHEEL
fenrir_api-0.1.4.dist-info/top_level.txt
fenrir_api-0.1.4.dist-info/RECORD
